opensdpc/OpenSdpc.py
opensdpc/Sdpc_struct.py
opensdpc/__init__.py
opensdpc/normalizeStaining.py
opensdpc/LINUX/libDecodeHevc.so
opensdpc/LINUX/libDecodeSdpc.so
opensdpc/LINUX/ffmpeg/libavcodec.so
opensdpc/LINUX/ffmpeg/libavcodec.so.58
opensdpc/LINUX/ffmpeg/libavcodec.so.58.111.100
opensdpc/LINUX/ffmpeg/libavdevice.so
opensdpc/LINUX/ffmpeg/libavdevice.so.58
opensdpc/LINUX/ffmpeg/libavdevice.so.58.11.102
opensdpc/LINUX/ffmpeg/libavfilter.so
opensdpc/LINUX/ffmpeg/libavfilter.so.7
opensdpc/LINUX/ffmpeg/libavfilter.so.7.87.100
opensdpc/LINUX/ffmpeg/libavformat.so
opensdpc/LINUX/ffmpeg/libavformat.so.58
opensdpc/LINUX/ffmpeg/libavformat.so.58.62.100
opensdpc/LINUX/ffmpeg/libavutil.so
opensdpc/LINUX/ffmpeg/libavutil.so.56
opensdpc/LINUX/ffmpeg/libavutil.so.56.60.100
opensdpc/LINUX/ffmpeg/libswresample.so
opensdpc/LINUX/ffmpeg/libswresample.so.3
opensdpc/LINUX/ffmpeg/libswresample.so.3.8.100
opensdpc/LINUX/ffmpeg/libswscale.so
opensdpc/LINUX/ffmpeg/libswscale.so.5
opensdpc/LINUX/ffmpeg/libswscale.so.5.8.100
opensdpc/LINUX/ffmpeg/libx264.so
opensdpc/LINUX/ffmpeg/libx264.so.148
opensdpc/LINUX/ffmpeg/libx265.so
opensdpc/LINUX/ffmpeg/libx265.so.79
opensdpc/LINUX/jpeg/libjpeg.a
opensdpc/LINUX/jpeg/libjpeg.so
opensdpc/LINUX/jpeg/libjpeg.so.8
opensdpc/LINUX/jpeg/libjpeg.so.8.2.2
opensdpc/LINUX/jpeg/libturbojpeg.a
opensdpc/LINUX/jpeg/libturbojpeg.so
opensdpc/LINUX/jpeg/libturbojpeg.so.0
opensdpc/LINUX/jpeg/libturbojpeg.so.0.2.0
opensdpc-1.0.0.dist-info/METADATA
opensdpc-1.0.0.dist-info/WHEEL
opensdpc-1.0.0.dist-info/top_level.txt
opensdpc-1.0.0.dist-info/RECORD
